viai/__init__.py
viai/images.py
viai/modules.py
viai/solutions.py
viai_sdk-0.1.16.dist-info/LICENSE
viai_sdk-0.1.16.dist-info/METADATA
viai_sdk-0.1.16.dist-info/WHEEL
viai_sdk-0.1.16.dist-info/top_level.txt
viai_sdk-0.1.16.dist-info/RECORD
