Metadata-Version: 2.1
Name: viai-sdk
Version: 0.1.16
Summary: A Python SDK for the Google Cloud Visual Inspection AI product
Author-email: Jamie Duncan <jamieduncan@google.com>
License: 
Project-URL: Homepage, https://github.com/google/viai-sdk
Project-URL: Bug Tracker, https://github.com/google/viai-sdk/issues
Classifier: Programming Language :: Python :: 3
Classifier: Operating System :: OS Independent
Classifier: License :: OSI Approved :: Apache Software License
Requires-Python: >=3.7
License-File: LICENSE
Requires-Dist: google-auth
Requires-Dist: google-oauth
Requires-Dist: google-cloud
Requires-Dist: google-cloud-storage
Provides-Extra: dev
Requires-Dist: nose2 ; extra == 'dev'
Requires-Dist: coverage ; extra == 'dev'
Requires-Dist: bump2version ; extra == 'dev'
